{
  "isRarV5" : false,
  "isEncrypted" : false,
  "isPasswordProtected" : false,
  "isOldFormat" : false,
  "fileHeaders" : [ {
    "archivalTime" : null,
    "lastAccessTime" : null,
    "lastModifiedTime" : 1527158966.921877900,
    "creationTime" : null,
    "fileCRC" : -2074010743,
    "fileName" : "اداره کل پست\\12-10.xlsx",
    "hostOS" : "win32",
    "fullPackSize" : 11747,
    "fullUnpackSize" : 14870,
    "isSolid" : false,
    "isEncrypted" : false,
    "isUnicode" : true,
    "hasExtTime" : true,
    "isLargeBlock" : false,
    "isDirectory" : false
  }, {
    "archivalTime" : null,
    "lastAccessTime" : null,
    "lastModifiedTime" : 1527159356.753267600,
    "creationTime" : null,
    "fileCRC" : -1972124867,
    "fileName" : "اداره کل پست\\12-11.xlsx",
    "hostOS" : "win32",
    "fullPackSize" : 11269,
    "fullUnpackSize" : 14356,
    "isSolid" : false,
    "isEncrypted" : false,
    "isUnicode" : true,
    "hasExtTime" : true,
    "isLargeBlock" : false,
    "isDirectory" : false
  }, {
    "archivalTime" : null,
    "lastAccessTime" : null,
    "lastModifiedTime" : 1527156765.628406600,
    "creationTime" : null,
    "fileCRC" : 866437043,
    "fileName" : "اداره کل پست\\12-8.xlsx",
    "hostOS" : "win32",
    "fullPackSize" : 12171,
    "fullUnpackSize" : 15419,
    "isSolid" : false,
    "isEncrypted" : false,
    "isUnicode" : true,
    "hasExtTime" : true,
    "isLargeBlock" : false,
    "isDirectory" : false
  }, {
    "archivalTime" : null,
    "lastAccessTime" : null,
    "lastModifiedTime" : 1528975431.517863200,
    "creationTime" : null,
    "fileCRC" : 485777453,
    "fileName" : "اداره کل پست\\12-9.xlsx",
    "hostOS" : "win32",
    "fullPackSize" : 12049,
    "fullUnpackSize" : 15322,
    "isSolid" : false,
    "isEncrypted" : false,
    "isUnicode" : true,
    "hasExtTime" : true,
    "isLargeBlock" : false,
    "isDirectory" : false
  }, {
    "archivalTime" : null,
    "lastAccessTime" : null,
    "lastModifiedTime" : 1529924572.291843900,
    "creationTime" : null,
    "fileCRC" : 517443982,
    "fileName" : "اداره کل پست\\تعاریف و مفاهیم فصل 12.docx",
    "hostOS" : "win32",
    "fullPackSize" : 11710,
    "fullUnpackSize" : 14585,
    "isSolid" : false,
    "isEncrypted" : false,
    "isUnicode" : true,
    "hasExtTime" : true,
    "isLargeBlock" : false,
    "isDirectory" : false
  }, {
    "archivalTime" : null,
    "lastAccessTime" : null,
    "lastModifiedTime" : 1529926345.331637000,
    "creationTime" : null,
    "fileCRC" : 0,
    "fileName" : "اداره کل پست",
    "hostOS" : "win32",
    "fullPackSize" : 0,
    "fullUnpackSize" : 0,
    "isSolid" : false,
    "isEncrypted" : false,
    "isUnicode" : true,
    "hasExtTime" : true,
    "isLargeBlock" : false,
    "isDirectory" : true
  } ],
  "exception" : null
}