{
  "isRarV5" : false,
  "isEncrypted" : false,
  "isPasswordProtected" : false,
  "isOldFormat" : false,
  "fileHeaders" : [ {
    "archivalTime" : null,
    "lastAccessTime" : null,
    "lastModifiedTime" : 1367940634.187500000,
    "creationTime" : null,
    "fileCRC" : -2040038172,
    "fileName" : "Лялька-мотанка\\1.jpg",
    "hostOS" : "win32",
    "fullPackSize" : 11719,
    "fullUnpackSize" : 11929,
    "isSolid" : false,
    "isEncrypted" : false,
    "isUnicode" : true,
    "hasExtTime" : true,
    "isLargeBlock" : false,
    "isDirectory" : false
  }, {
    "archivalTime" : null,
    "lastAccessTime" : null,
    "lastModifiedTime" : 1367940646.453125000,
    "creationTime" : null,
    "fileCRC" : -1200673113,
    "fileName" : "Лялька-мотанка\\2.jpg",
    "hostOS" : "win32",
    "fullPackSize" : 14547,
    "fullUnpackSize" : 14727,
    "isSolid" : false,
    "isEncrypted" : false,
    "isUnicode" : true,
    "hasExtTime" : true,
    "isLargeBlock" : false,
    "isDirectory" : false
  }, {
    "archivalTime" : null,
    "lastAccessTime" : null,
    "lastModifiedTime" : 1367940653.421875000,
    "creationTime" : null,
    "fileCRC" : 89328870,
    "fileName" : "Лялька-мотанка\\3.jpg",
    "hostOS" : "win32",
    "fullPackSize" : 25508,
    "fullUnpackSize" : 25585,
    "isSolid" : false,
    "isEncrypted" : false,
    "isUnicode" : true,
    "hasExtTime" : true,
    "isLargeBlock" : false,
    "isDirectory" : false
  }, {
    "archivalTime" : null,
    "lastAccessTime" : null,
    "lastModifiedTime" : 1367940686.578125000,
    "creationTime" : null,
    "fileCRC" : -126621757,
    "fileName" : "Лялька-мотанка\\4.jpg",
    "hostOS" : "win32",
    "fullPackSize" : 31100,
    "fullUnpackSize" : 31485,
    "isSolid" : false,
    "isEncrypted" : false,
    "isUnicode" : true,
    "hasExtTime" : true,
    "isLargeBlock" : false,
    "isDirectory" : false
  }, {
    "archivalTime" : null,
    "lastAccessTime" : null,
    "lastModifiedTime" : 1368376918.968750000,
    "creationTime" : null,
    "fileCRC" : 396988820,
    "fileName" : "Лялька-мотанка\\Баба-берегиня.JPG",
    "hostOS" : "win32",
    "fullPackSize" : 52585,
    "fullUnpackSize" : 54447,
    "isSolid" : false,
    "isEncrypted" : false,
    "isUnicode" : true,
    "hasExtTime" : true,
    "isLargeBlock" : false,
    "isDirectory" : false
  }, {
    "archivalTime" : null,
    "lastAccessTime" : null,
    "lastModifiedTime" : 1366740070.000000000,
    "creationTime" : null,
    "fileCRC" : -456745492,
    "fileName" : "Лялька-мотанка\\На  підсумок.png",
    "hostOS" : "win32",
    "fullPackSize" : 363411,
    "fullUnpackSize" : 363411,
    "isSolid" : false,
    "isEncrypted" : false,
    "isUnicode" : true,
    "hasExtTime" : false,
    "isLargeBlock" : false,
    "isDirectory" : false
  }, {
    "archivalTime" : null,
    "lastAccessTime" : null,
    "lastModifiedTime" : 1366898541.484375000,
    "creationTime" : null,
    "fileCRC" : -1401931587,
    "fileName" : "Лялька-мотанка\\Найбільша мотанка.jpg",
    "hostOS" : "win32",
    "fullPackSize" : 54309,
    "fullUnpackSize" : 54309,
    "isSolid" : false,
    "isEncrypted" : false,
    "isUnicode" : true,
    "hasExtTime" : true,
    "isLargeBlock" : false,
    "isDirectory" : false
  }, {
    "archivalTime" : null,
    "lastAccessTime" : null,
    "lastModifiedTime" : 1367996280.000000000,
    "creationTime" : null,
    "fileCRC" : -194979210,
    "fileName" : "Лялька-мотанка\\Наречена.jpg",
    "hostOS" : "win32",
    "fullPackSize" : 127290,
    "fullUnpackSize" : 149602,
    "isSolid" : false,
    "isEncrypted" : false,
    "isUnicode" : true,
    "hasExtTime" : false,
    "isLargeBlock" : false,
    "isDirectory" : false
  }, {
    "archivalTime" : null,
    "lastAccessTime" : null,
    "lastModifiedTime" : 1367995678.000000000,
    "creationTime" : null,
    "fileCRC" : -1050699248,
    "fileName" : "Лялька-мотанка\\Немовля.jpg",
    "hostOS" : "win32",
    "fullPackSize" : 8808,
    "fullUnpackSize" : 8952,
    "isSolid" : false,
    "isEncrypted" : false,
    "isUnicode" : true,
    "hasExtTime" : false,
    "isLargeBlock" : false,
    "isDirectory" : false
  }, {
    "archivalTime" : null,
    "lastAccessTime" : null,
    "lastModifiedTime" : 1368366066.109375000,
    "creationTime" : null,
    "fileCRC" : 398458442,
    "fileName" : "Лялька-мотанка\\Обрядові1.jpg",
    "hostOS" : "win32",
    "fullPackSize" : 67875,
    "fullUnpackSize" : 67875,
    "isSolid" : false,
    "isEncrypted" : false,
    "isUnicode" : true,
    "hasExtTime" : true,
    "isLargeBlock" : false,
    "isDirectory" : false
  }, {
    "archivalTime" : null,
    "lastAccessTime" : null,
    "lastModifiedTime" : 1368367597.203125000,
    "creationTime" : null,
    "fileCRC" : -1938862162,
    "fileName" : "Лялька-мотанка\\Обрядові2.jpg",
    "hostOS" : "win32",
    "fullPackSize" : 61346,
    "fullUnpackSize" : 61357,
    "isSolid" : false,
    "isEncrypted" : false,
    "isUnicode" : true,
    "hasExtTime" : true,
    "isLargeBlock" : false,
    "isDirectory" : false
  }, {
    "archivalTime" : null,
    "lastAccessTime" : null,
    "lastModifiedTime" : 1366888351.109375000,
    "creationTime" : null,
    "fileCRC" : -617501765,
    "fileName" : "Лялька-мотанка\\Опис ляльки.jpg",
    "hostOS" : "win32",
    "fullPackSize" : 249012,
    "fullUnpackSize" : 266231,
    "isSolid" : false,
    "isEncrypted" : false,
    "isUnicode" : true,
    "hasExtTime" : true,
    "isLargeBlock" : false,
    "isDirectory" : false
  } ],
  "exception" : null
}