{
  "isRarV5" : false,
  "isEncrypted" : false,
  "isPasswordProtected" : false,
  "isOldFormat" : false,
  "fileHeaders" : [ {
    "archivalTime" : null,
    "lastAccessTime" : null,
    "lastModifiedTime" : 1193220110.000000000,
    "creationTime" : null,
    "fileCRC" : "C657A26A",
    "fileName" : "Spektr\\spektr.ini",
    "hostOS" : "win32",
    "fullPackSize" : 79,
    "fullUnpackSize" : 79,
    "isSolid" : false,
    "isEncrypted" : false,
    "isUnicode" : false,
    "hasExtTime" : false,
    "isLargeBlock" : false,
    "isDirectory" : false
  }, {
    "archivalTime" : null,
    "lastAccessTime" : null,
    "lastModifiedTime" : 1192149866.000000000,
    "creationTime" : null,
    "fileCRC" : "935F9E7B",
    "fileName" : "Spektr\\Spektr.exe",
    "hostOS" : "win32",
    "fullPackSize" : 295963,
    "fullUnpackSize" : 841728,
    "isSolid" : false,
    "isEncrypted" : false,
    "isUnicode" : false,
    "hasExtTime" : false,
    "isLargeBlock" : false,
    "isDirectory" : false
  }, {
    "archivalTime" : null,
    "lastAccessTime" : null,
    "lastModifiedTime" : 1056208564.000000000,
    "creationTime" : null,
    "fileCRC" : "F9FDE44F",
    "fileName" : "Spektr\\SPEKTR.CHM",
    "hostOS" : "win32",
    "fullPackSize" : 126260,
    "fullUnpackSize" : 133428,
    "isSolid" : false,
    "isEncrypted" : false,
    "isUnicode" : false,
    "hasExtTime" : false,
    "isLargeBlock" : false,
    "isDirectory" : false
  }, {
    "archivalTime" : null,
    "lastAccessTime" : null,
    "lastModifiedTime" : 1192149986.000000000,
    "creationTime" : null,
    "fileCRC" : "FE2E75DA",
    "fileName" : "Spektr\\SpektrView.exe",
    "hostOS" : "win32",
    "fullPackSize" : 219610,
    "fullUnpackSize" : 619008,
    "isSolid" : false,
    "isEncrypted" : false,
    "isUnicode" : false,
    "hasExtTime" : false,
    "isLargeBlock" : false,
    "isDirectory" : false
  }, {
    "archivalTime" : null,
    "lastAccessTime" : null,
    "lastModifiedTime" : 1291752174.000000000,
    "creationTime" : null,
    "fileCRC" : "0",
    "fileName" : "Spektr",
    "hostOS" : "win32",
    "fullPackSize" : 0,
    "fullUnpackSize" : 0,
    "isSolid" : false,
    "isEncrypted" : false,
    "isUnicode" : false,
    "hasExtTime" : false,
    "isLargeBlock" : false,
    "isDirectory" : true
  } ],
  "exception" : null
}