{
  "isRarV5" : false,
  "isEncrypted" : false,
  "isPasswordProtected" : false,
  "isOldFormat" : false,
  "fileHeaders" : [ {
    "archivalTime" : null,
    "lastAccessTime" : null,
    "lastModifiedTime" : 1522463236.532668100,
    "creationTime" : null,
    "fileCRC" : -67951308,
    "fileName" : "Chah1397\\Chah1397.pdf",
    "hostOS" : "win32",
    "fullPackSize" : 811947,
    "fullUnpackSize" : 854226,
    "isSolid" : false,
    "isEncrypted" : false,
    "isUnicode" : false,
    "hasExtTime" : true,
    "isLargeBlock" : false,
    "isDirectory" : false
  }, {
    "archivalTime" : null,
    "lastAccessTime" : null,
    "lastModifiedTime" : 1496803209.223198600,
    "creationTime" : null,
    "fileCRC" : 1843631144,
    "fileName" : "Chah1397\\نرم افزار آنالیز و برآورد قیمت دانا.url",
    "hostOS" : "win32",
    "fullPackSize" : 192,
    "fullUnpackSize" : 313,
    "isSolid" : false,
    "isEncrypted" : false,
    "isUnicode" : true,
    "hasExtTime" : true,
    "isLargeBlock" : false,
    "isDirectory" : false
  }, {
    "archivalTime" : null,
    "lastAccessTime" : null,
    "lastModifiedTime" : 1496803279.989754700,
    "creationTime" : null,
    "fileCRC" : -1784957031,
    "fileName" : "Chah1397\\نرم افزار تعیین دامنه قیمت دانا.url",
    "hostOS" : "win32",
    "fullPackSize" : 198,
    "fullUnpackSize" : 313,
    "isSolid" : false,
    "isEncrypted" : false,
    "isUnicode" : true,
    "hasExtTime" : true,
    "isLargeBlock" : false,
    "isDirectory" : false
  }, {
    "archivalTime" : null,
    "lastAccessTime" : null,
    "lastModifiedTime" : 1496803320.948174300,
    "creationTime" : null,
    "fileCRC" : -1815198420,
    "fileName" : "Chah1397\\نرم افزار جامع تعدیل دانا.url",
    "hostOS" : "win32",
    "fullPackSize" : 164,
    "fullUnpackSize" : 220,
    "isSolid" : false,
    "isEncrypted" : false,
    "isUnicode" : true,
    "hasExtTime" : true,
    "isLargeBlock" : false,
    "isDirectory" : false
  }, {
    "archivalTime" : null,
    "lastAccessTime" : null,
    "lastModifiedTime" : 1496803235.399164800,
    "creationTime" : null,
    "fileCRC" : -983464201,
    "fileName" : "Chah1397\\نرم افزار صورت وضعیت و برآورد اولیه دانا.url",
    "hostOS" : "win32",
    "fullPackSize" : 179,
    "fullUnpackSize" : 276,
    "isSolid" : false,
    "isEncrypted" : false,
    "isUnicode" : true,
    "hasExtTime" : true,
    "isLargeBlock" : false,
    "isDirectory" : false
  }, {
    "archivalTime" : null,
    "lastAccessTime" : null,
    "lastModifiedTime" : 1496803352.052439800,
    "creationTime" : null,
    "fileCRC" : -806229572,
    "fileName" : "Chah1397\\نرم افزار پیشنهاد قیمت دانا.url",
    "hostOS" : "win32",
    "fullPackSize" : 178,
    "fullUnpackSize" : 244,
    "isSolid" : false,
    "isEncrypted" : false,
    "isUnicode" : true,
    "hasExtTime" : true,
    "isLargeBlock" : false,
    "isDirectory" : false
  }, {
    "archivalTime" : null,
    "lastAccessTime" : null,
    "lastModifiedTime" : 1522464315.023281300,
    "creationTime" : null,
    "fileCRC" : 0,
    "fileName" : "Chah1397",
    "hostOS" : "win32",
    "fullPackSize" : 0,
    "fullUnpackSize" : 0,
    "isSolid" : false,
    "isEncrypted" : false,
    "isUnicode" : false,
    "hasExtTime" : true,
    "isLargeBlock" : false,
    "isDirectory" : true
  } ],
  "exception" : null
}