{
  "isRarV5" : false,
  "isEncrypted" : false,
  "isPasswordProtected" : false,
  "isOldFormat" : false,
  "fileHeaders" : [ {
    "archivalTime" : null,
    "lastAccessTime" : null,
    "lastModifiedTime" : 1152528460.755720500,
    "creationTime" : null,
    "fileCRC" : "BF309D26",
    "fileName" : "tn_IMGP7609.JPG",
    "hostOS" : "win32",
    "fullPackSize" : 3005,
    "fullUnpackSize" : 64781,
    "isSolid" : true,
    "isEncrypted" : false,
    "isUnicode" : false,
    "hasExtTime" : true,
    "isLargeBlock" : false,
    "isDirectory" : false
  }, {
    "archivalTime" : null,
    "lastAccessTime" : null,
    "lastModifiedTime" : 1152528461.911963100,
    "creationTime" : null,
    "fileCRC" : "D862F215",
    "fileName" : "tn_IMGP7610.JPG",
    "hostOS" : "win32",
    "fullPackSize" : 55969,
    "fullUnpackSize" : 59795,
    "isSolid" : true,
    "isEncrypted" : false,
    "isUnicode" : false,
    "hasExtTime" : true,
    "isLargeBlock" : false,
    "isDirectory" : false
  }, {
    "archivalTime" : null,
    "lastAccessTime" : null,
    "lastModifiedTime" : 1152528463.068205700,
    "creationTime" : null,
    "fileCRC" : "7DEEE654",
    "fileName" : "tn_IMGP7611.JPG",
    "hostOS" : "win32",
    "fullPackSize" : 51196,
    "fullUnpackSize" : 54426,
    "isSolid" : false,
    "isEncrypted" : false,
    "isUnicode" : false,
    "hasExtTime" : true,
    "isLargeBlock" : false,
    "isDirectory" : false
  }, {
    "archivalTime" : null,
    "lastAccessTime" : null,
    "lastModifiedTime" : 1152528464.224448300,
    "creationTime" : null,
    "fileCRC" : "3401274E",
    "fileName" : "tn_IMGP7612.JPG",
    "hostOS" : "win32",
    "fullPackSize" : 78571,
    "fullUnpackSize" : 80107,
    "isSolid" : true,
    "isEncrypted" : false,
    "isUnicode" : false,
    "hasExtTime" : true,
    "isLargeBlock" : false,
    "isDirectory" : false
  }, {
    "archivalTime" : null,
    "lastAccessTime" : null,
    "lastModifiedTime" : 1152528465.411940700,
    "creationTime" : null,
    "fileCRC" : "B6E254B6",
    "fileName" : "tn_IMGP7613.JPG",
    "hostOS" : "win32",
    "fullPackSize" : 77338,
    "fullUnpackSize" : 78978,
    "isSolid" : true,
    "isEncrypted" : false,
    "isUnicode" : false,
    "hasExtTime" : true,
    "isLargeBlock" : false,
    "isDirectory" : false
  }, {
    "archivalTime" : null,
    "lastAccessTime" : null,
    "lastModifiedTime" : 1152528466.568183300,
    "creationTime" : null,
    "fileCRC" : "43C46EE9",
    "fileName" : "tn_IMGP7614.JPG",
    "hostOS" : "win32",
    "fullPackSize" : 90964,
    "fullUnpackSize" : 92380,
    "isSolid" : true,
    "isEncrypted" : false,
    "isUnicode" : false,
    "hasExtTime" : true,
    "isLargeBlock" : false,
    "isDirectory" : false
  }, {
    "archivalTime" : null,
    "lastAccessTime" : null,
    "lastModifiedTime" : 1152528467.771300600,
    "creationTime" : null,
    "fileCRC" : "304FE99A",
    "fileName" : "tn_IMGP7615.JPG",
    "hostOS" : "win32",
    "fullPackSize" : 86442,
    "fullUnpackSize" : 87925,
    "isSolid" : true,
    "isEncrypted" : false,
    "isUnicode" : false,
    "hasExtTime" : true,
    "isLargeBlock" : false,
    "isDirectory" : false
  }, {
    "archivalTime" : null,
    "lastAccessTime" : null,
    "lastModifiedTime" : 1152528468.990042800,
    "creationTime" : null,
    "fileCRC" : "A980C5E1",
    "fileName" : "tn_IMGP7616.JPG",
    "hostOS" : "win32",
    "fullPackSize" : 96294,
    "fullUnpackSize" : 97623,
    "isSolid" : true,
    "isEncrypted" : false,
    "isUnicode" : false,
    "hasExtTime" : true,
    "isLargeBlock" : false,
    "isDirectory" : false
  }, {
    "archivalTime" : null,
    "lastAccessTime" : null,
    "lastModifiedTime" : 1152528470.193160100,
    "creationTime" : null,
    "fileCRC" : "6C69BBE9",
    "fileName" : "tn_IMGP7617.JPG",
    "hostOS" : "win32",
    "fullPackSize" : 81180,
    "fullUnpackSize" : 82818,
    "isSolid" : true,
    "isEncrypted" : false,
    "isUnicode" : false,
    "hasExtTime" : true,
    "isLargeBlock" : false,
    "isDirectory" : false
  }, {
    "archivalTime" : null,
    "lastAccessTime" : null,
    "lastModifiedTime" : 1152528471.365027600,
    "creationTime" : null,
    "fileCRC" : "620C877B",
    "fileName" : "tn_IMGP7618.JPG",
    "hostOS" : "win32",
    "fullPackSize" : 89120,
    "fullUnpackSize" : 90581,
    "isSolid" : true,
    "isEncrypted" : false,
    "isUnicode" : false,
    "hasExtTime" : true,
    "isLargeBlock" : false,
    "isDirectory" : false
  }, {
    "archivalTime" : null,
    "lastAccessTime" : null,
    "lastModifiedTime" : 1152528472.568144900,
    "creationTime" : null,
    "fileCRC" : "3B353DDC",
    "fileName" : "tn_IMGP7619.JPG",
    "hostOS" : "win32",
    "fullPackSize" : 95123,
    "fullUnpackSize" : 96451,
    "isSolid" : true,
    "isEncrypted" : false,
    "isUnicode" : false,
    "hasExtTime" : true,
    "isLargeBlock" : false,
    "isDirectory" : false
  }, {
    "archivalTime" : null,
    "lastAccessTime" : null,
    "lastModifiedTime" : 1152528473.771262200,
    "creationTime" : null,
    "fileCRC" : "F781635A",
    "fileName" : "tn_IMGP7620.JPG",
    "hostOS" : "win32",
    "fullPackSize" : 95179,
    "fullUnpackSize" : 96609,
    "isSolid" : true,
    "isEncrypted" : false,
    "isUnicode" : false,
    "hasExtTime" : true,
    "isLargeBlock" : false,
    "isDirectory" : false
  }, {
    "archivalTime" : null,
    "lastAccessTime" : null,
    "lastModifiedTime" : 1152528475.240002800,
    "creationTime" : null,
    "fileCRC" : "A96F1200",
    "fileName" : "tn_IMGP7621.JPG",
    "hostOS" : "win32",
    "fullPackSize" : 88319,
    "fullUnpackSize" : 96840,
    "isSolid" : true,
    "isEncrypted" : false,
    "isUnicode" : false,
    "hasExtTime" : true,
    "isLargeBlock" : false,
    "isDirectory" : false
  } ],
  "exception" : null
}